Workbook

Sheet 00_Cover
A1: SQL BUSINESS REPORTING — PORTFOLIO OUTPUT PACK
A2: Governed SQL results, quality controls, metric definitions, and Power BI handoff
A4: PROJECT OVERVIEW
A5: Controlled evidence pack for a fictional Luxembourg-headquartered European e-commerce retailer using UCI Online Retail II. Excel documents reconciled SQL outputs and governance; Power BI is the visualization layer.
A8: PROJECT FACTS
A10: Project Title | B10: SQL Business Reporting Portfolio Project | C10: Business Scenario | D10: Luxembourg-headquartered European e-commerce retailer | E10: Dataset Source | F10: UCI Online Retail II | G10: Author | H10: Joy Lorna
A11: Reporting Layer | B11: Excel output pack and Power BI dashboard | C11: Analytical Grain | D11: One invoice line per product per invoice | E11: Reporting Period | F11: Dec 2009 – Dec 2011 | G11: Version | H11: v1.0
A12: Source Currency Treatment | B12: Unit prices treated as GBP; no FX conversion applied | C12: Workbook Role | D12: Reconciled SQL output pack | E12: Data As Of | F12: Dec 2011 | G12: Last Updated | H12: Aug 2026
A13: PORTFOLIO DISCLOSURE
A14: This project uses the publicly available UCI Online Retail II dataset. The Luxembourg business context, reporting structure, management commentary and analytical outputs are simulated for portfolio and educational purposes. No real company data, customer data or proprietary commercial information is used.
A17: START HERE
A18: Sheet | B18: Purpose
A19: 01_Executive_Summary | B19: Results, insights, and limitations
A20: 02_Workbook_Index | B20: Output inventory
A21: 03_Data_Model_And_Architecture | B21: Source-to-report architecture
A22: 04_Metric_Dictionary | B22: Metric definitions
A23: 05_Validation_Summary | B23: Consolidated controls
A24: 06_Power_BI_Handoff | B24: Power BI page mapping
A25: DQ01_Raw_Profile | B25: Source profile
A26: DQ02_Row_Reconciliation | B26: Row completeness
A27: DQ03_Revenue_Reconciliation | B27: Financial reconciliation
A28: DQ04_Orphan_Key_Check | B28: Key integrity
A29: DQ05_Cancellation_Profile | B29: Cancellation profile
... A39: Q10_Rolling_Revenue | B39: Smoothed three-month revenue trend

Sheet 01_Executive_Summary
A1: EXECUTIVE SUMMARY
A2: Purpose, architecture, reconciled results, business insights, and Power BI next step
A4: 1. PROJECT PURPOSE
A5: Translate ten stakeholder questions into governed SQL outputs supported by a dimensional model, controlled metric logic, and reconciliation checks. This workbook is the reconciled evidence and handoff layer; Power BI remains the visualization and interaction layer.
A8: 2. ARCHITECTURE SUMMARY
A9: UCI source extracts → standardized staging → invoice-line fact table with date, customer, product, and country dimensions → validation controls → ten named Excel Tables → Power BI reporting pages.
A12: 3. RECONCILED RESULTS
A14: Control | B14: Result | C14: Status
A15: Row reconciliation difference | B15: =DQ02_Row_Reconciliation!C8 -> 0 | C15: =DQ02_Row_Reconciliation!D8 -> PASS
A16: Revenue reconciliation difference | B16: =DQ03_Revenue_Reconciliation!C8 -> 0 | C16: =DQ03_Revenue_Reconciliation!D8 -> PASS
A17: Missing dimension keys | B17: =SUM(DQ04_Orphan_Key_Check!B8:B10) -> 0 | C17: =IF(B17=0,"PASS","FAIL") -> PASS
A18: Rows profiled | B18: =DQ01_Raw_Profile!C8 -> 1067371 | C18: COMPLETE
A19: Net revenue reconciled | B19: =DQ01_Raw_Profile!C21 -> 19287251 | C19: PASS
A21: 4. KEY BUSINESS INSIGHTS
A23: 1 | B23: Revenue is highly seasonal; November 2011 produced the strongest monthly gross revenue at £1,509,496.33.
A24: 2 | B24: The United Kingdom contributes £14,723,147.52 of attributed country revenue, creating both commercial strength and concentration risk.
A25: 3 | B25: Other or uncategorised products contribute 39.4% of category revenue, indicating a material classification-governance gap.
A26: 4 | B26: The top ten customers contribute 15.9% of identified-customer revenue, so value is concentrated but not dependent on one customer group.
A27: 5 | B27: Cancellation exposure should be assessed using both value and rate because small markets can show volatile rates on low sales volume.
A29: 5. LIMITATIONS AND POWER BI NEXT STEP
A31: Limitations: 243,007 rows have missing customer IDs; product categories are derived and retain a 39.4% uncategorised share; unit prices are treated as GBP with no FX conversion; revenue is highly UK-concentrated; and cancellation rates are volatile in low-volume countries. Next step: load the named Excel Tables into Power BI and build the five pages mapped in 06_Power_BI_Handoff.

Sheet 02_Workbook_Index
A1: WORKBOOK INDEX
A2: Controlled inventory of documentation, validation, and business-query outputs
A5: Sheet Name | B5: Section | C5: Purpose | D5: Power BI Used? | E5: Source / Reference | F5: Review Status
A6: 00_Cover | B6: Documentation | C6: Project scope and navigation | D6: No | E6: README.md | F6: Prepared
A7: 01_Executive_Summary | B7: Documentation | C7: Results, insights, and limitations | D7: Yes | E7: README.md | F7: Verified
A8: 02_Workbook_Index | B8: Governance | C8: Output inventory | D8: No | E8: query_catalogue.md | F8: Prepared
A9: 03_Data_Model_And_Architecture | B9: Governance | C9: Source-to-report architecture | D9: Yes | E9: schema.sql | F9: Prepared
A10: 04_Metric_Dictionary | B10: Governance | C10: Metric definitions | D10: Yes | E10: metric_dictionary.md | F10: Prepared
A11: 05_Validation_Summary | B11: Validation | C11: Consolidated controls | D11: No | E11: data_quality_checks.sql | F11: Complete
A12: 06_Power_BI_Handoff | B12: Handoff | C12: Power BI page mapping | D12: Yes | E12: power_bi_handoff.md | F12: Prepared
A13: DQ01_Raw_Profile | B13: Validation | C13: Source profile | D13: No | E13: data_quality_checks.sql | F13: Complete
A14: DQ02_Row_Reconciliation | B14: Validation | C14: Row completeness | D14: No | E14: data_quality_checks.sql | F14: Complete
A15: DQ03_Revenue_Reconciliation | B15: Validation | C15: Financial reconciliation | D15: No | E15: data_quality_checks.sql | F15: Complete
A16: DQ04_Orphan_Key_Check | B16: Validation | C16: Key integrity | D16: No | E16: data_quality_checks.sql | F16: Complete
... A27: Q10_Rolling_Revenue | B27: Business Query | C27: Smoothed three-month revenue trend | D27: Yes | E27: 10_rolling_revenue.sql | F27: Verified

Sheet 03_Data_Model_And_Architecture
A1: DATA MODEL AND ARCHITECTURE
A2: Source-to-report flow, grain, entities, and control points
A5: Step | B5: Layer | C5: Purpose | D5: Output
A6: 1 | B6: Raw files | C6: Retain UCI extracts | D6: 2009–10 and 2010–11 files
A7: 2 | B7: Staging | C7: Clean, type, and enrich | D7: Typed staging table
A8: 3 | B8: Star schema | C8: Resolve conformed dimensions | D8: Fact sales plus date, customer, product, country
A9: 4 | B9: Validation | C9: Reconcile volume, revenue, and keys | D9: DQ01–DQ05
A10: 5 | B10: Reporting | C10: Answer ten questions | D10: Q01–Q10 named Tables
A11: 6 | B11: Power BI | C11: Model and visualize prepared outputs | D11: Five report pages
A13: Analytical grain: one invoice line per product per invoice. Final reporting grain: one row per query output record in Excel; one invoice line per row in the BigQuery fact table. Unit prices are treated as GBP with no FX conversion. Missing customer IDs and derived product categories remain documented limitations.

Sheet 04_Metric_Dictionary
A1: METRIC DICTIONARY
A2: Governed definitions used across SQL outputs and Power BI
A5: Metric | B5: Definition | C5: Formula / Logic | D5: Included Rows | E5: Excluded Rows | F5: Used In
A6: Gross Revenue | B6: Non-cancelled sales value before cancellation rows are netted back. | C6: SUM(gross_revenue) where is_cancelled = FALSE | D6: Non-cancelled lines | E6: Cancellation lines | F6: Q01; Q04
A7: Net Revenue | B7: Revenue after cancellations | C7: SUM all gross_revenue | D7: All fact rows | E7: None | F7: DQ03; Q01
A8: Cancellation Rate | B8: Cancelled value / gross sales | C8: Cancelled Value / Gross Sales Value | D8: All sales/cancellations | E8: Zero gross sales | F8: Q05
A9: Average Order Value | B9: Gross revenue / orders | C9: Gross Revenue / distinct invoices | D9: Non-cancelled invoices | E9: Cancellations | F9: Q01; Q02
A10: Revenue per Customer | B10: Revenue / active customers | C10: Revenue / distinct customer IDs | D10: Identified customers | E10: Missing IDs | F10: Q04
A11: Running Revenue | B11: Cumulative monthly revenue | C11: SUM OVER ordered months | D11: All months | E11: None | F11: Q06
A12: MoM Growth | B12: Change from prior month | C12: (Revenue-Prior)/Prior | D12: Months with prior | E12: First month | F12: Q09
A13: Rolling 3-Month Average | B13: Smoothed revenue | C13: AVG current and prior 2 months | D13: Available months | E13: None | F13: Q10

Sheet 05_Validation_Summary
A1: VALIDATION SUMMARY
A2: Consolidated completeness, financial, and key-integrity controls
A5: Control | B5: Criterion | C5: Result | D5: Status | E5: Detail Sheet
A6: Row completeness | B6: Difference = 0 | C6: =DQ02_Row_Reconciliation!C8 -> 0 | D6: =DQ02_Row_Reconciliation!D8 -> PASS | E6: DQ02_Row_Reconciliation
A7: Revenue reconciliation | B7: Abs difference < £0.01 | C7: =DQ03_Revenue_Reconciliation!C8 -> 0 | D7: =DQ03_Revenue_Reconciliation!D8 -> PASS | E7: DQ03_Revenue_Reconciliation
A8: Product keys | B8: Missing = 0 | C8: =DQ04_Orphan_Key_Check!B8 -> 0 | D8: =DQ04_Orphan_Key_Check!C8 -> PASS | E8: DQ04_Orphan_Key_Check
A9: Country keys | B9: Missing = 0 | C9: =DQ04_Orphan_Key_Check!B9 -> 0 | D9: =DQ04_Orphan_Key_Check!C9 -> PASS | E9: DQ04_Orphan_Key_Check
A10: Date keys | B10: Missing = 0 | C10: =DQ04_Orphan_Key_Check!B10 -> 0 | D10: =DQ04_Orphan_Key_Check!C10 -> PASS | E10: DQ04_Orphan_Key_Check
A11: Missing Customer ID | B11: Profiled limitation | C11: =DQ01_Raw_Profile!C15 -> 243007 | D11: MONITOR | E11: DQ01_Raw_Profile
A12: Missing Customer ID % | B12: Profiled limitation | C12: 0.22766873 | D12: MONITOR | E12: DQ01_Raw_Profile

Sheet 06_Power_BI_Handoff
A1: POWER BI HANDOFF
A2: Named Excel Tables mapped to report pages, visuals, fields, and purpose
A5: Power BI Page | B5: Excel Source Sheet / Table | C5: Main Visuals | D5: Key Fields | E5: Purpose
A6: Executive Overview | B6: Q01_Monthly_Revenue (tbl_q01_monthly_revenue); Q04_Country_Performance (tbl_q04_country_performance); Q03_Product_Category (tbl_q03_product_category) | C6: KPI cards; revenue trend; country bar; category bar | D6: Gross Revenue; Net Revenue; Orders; Country; Category | E6: Shows high-level business performance
A7: Customer Analytics | B7: Q02_Top_Customers (tbl_q02_top_customers); Q07_Customer_Cohorts (tbl_q07_customer_cohorts) | C7: Top-customer table; cohort chart; customer value cards | D7: Customer ID; Revenue; Orders; Cohort Month | E7: Explains customer value and acquisition behaviour
A8: Product Analytics | B8: Q03_Product_Category (tbl_q03_product_category) | C8: Category revenue bar; units by category; product count | D8: Category; Revenue; Units; Product Count | E8: Explains product mix and category concentration
A9: Geographic Analytics | B9: Q04_Country_Performance (tbl_q04_country_performance); Q08_Regional_Ranking (tbl_q08_regional_ranking) | C9: Country ranking; regional performance; revenue per customer | D9: Country; Region; Revenue; Revenue Per Customer | E9: Explains geographic concentration and expansion opportunity
A10: Revenue Trend | B10: Q01_Monthly_Revenue (tbl_q01_monthly_revenue); Q06_Running_Revenue (tbl_q06_running_revenue); Q09_MoM_Growth (tbl_q09_mom_growth); Q10_Rolling_Revenue (tbl_q10_rolling_revenue) | C10: Line charts; growth chart; rolling average | D10: Year Month; Revenue; Running Total; Pct Change | E10: Explains seasonality and momentum

Sheet DQ01_Raw_Profile
A1: Raw Data Profile
A2: Purpose: Validate raw data coverage and quality before analysis.
A3: Business Use: Confirms the dataset supports customer, product, country, cancellation, and revenue reporting.
A4: Power BI Use: Supports executive KPI cards and data-quality notes.
A5: Key Assumption: Source currency is GBP; dates are true dates; no FX conversion is applied.
A7: Category | B7: Metric | C7: Value | D7: Unit | E7: Status
A8: Dataset Coverage | B8: Total Rows | C8: 1067371 | D8: Rows | E8: PROFILED
A9: Dataset Coverage | B9: First Invoice Date | C9: 40148 | D9: Date | E9: PROFILED
A10: Dataset Coverage | B10: Last Invoice Date | C10: 40886 | D10: Date | E10: PROFILED
A11: Entity Coverage | B11: Distinct Invoices | C11: 53628 | D11: Invoices | E11: PROFILED
A12: Entity Coverage | B12: Distinct Stock Codes | C12: 5305 | D12: Products | E12: PROFILED
A13: Entity Coverage | B13: Distinct Customers | C13: 5942 | D13: Customers | E13: PROFILED
A14: Entity Coverage | B14: Distinct Countries | C14: 43 | D14: Countries | E14: PROFILED
A15: Data Quality Flags | B15: Rows Missing Customer ID | C15: 243007 | D15: Rows | E15: MONITOR
A16: Data Quality Flags | B16: Rows Missing Description | C16: 4382 | D16: Rows | E16: MONITOR
A17: Data Quality Flags | B17: Rows Negative Quantity | C17: 22950 | D17: Rows | E17: REVIEWED
A18: Data Quality Flags | B18: Rows Zero Unit Price | C18: 6202 | D18: Rows | E18: REVIEWED
A19: Cancellation Logic | B19: Cancellation Lines | C19: 19494 | D19: Rows | E19: REVIEWED
... A21: Cancellation Logic | B21: Total Net Revenue | C21: 19287251 | D21: GBP | E21: RECONCILED
A22: Calculated Rates | B22: Missing Customer ID % | C22: =C15/C8 -> 0.22766873 | D22: Percent | E22: MONITOR
A23: Calculated Rates | B23: Cancellation Line % | C23: =C19/C8 -> 0.018263565 | D23: Percent | E23: REVIEWED
A24: Calculated Rates | B24: Negative Quantity % | C24: =C17/C8 -> 0.021501427 | D24: Percent | E24: REVIEWED
A25: Calculated Rates | B25: Zero Unit Price % | C25: =C18/C8 -> 0.0058105382 | D25: Percent | E25: REVIEWED

Sheet DQ02_Row_Reconciliation
A1: Row-Count Reconciliation
A2: Purpose: Confirm every staging row is represented in the fact table.
A3: Business Use: Provides a completeness control before downstream reporting.
A4: Power BI Use: Retained as validation evidence; not loaded to the report model.
A5: Key Assumption: Staging and fact tables share the same invoice-line grain.
A7: Staging Rows | B7: Fact Rows | C7: Difference | D7: Status
A8: 1067371 | B8: 1067371 | C8: =B8-A8 -> 0 | D8: =IF(C8=0,"PASS","FAIL") -> PASS

Sheet DQ03_Revenue_Reconciliation
A1: Revenue Reconciliation
A2: Purpose: Confirm staging and fact revenue reconcile exactly.
A3: Business Use: Provides the core financial control for reporting outputs.
A4: Power BI Use: Retained as validation evidence; not loaded to the report model.
A5: Key Assumption: Both layers use source GBP and identical cancellation treatment.
A7: Staging Revenue | B7: Fact Revenue | C7: Difference | D7: Status
A8: 19287251 | B8: 19287251 | C8: =B8-A8 -> 0 | D8: =IF(ABS(C8)<0.01,"PASS","FAIL") -> PASS

Sheet DQ04_Orphan_Key_Check
A1: Orphan Key Check
A2: Purpose: Confirm fact-table keys resolve to product, country, and date dimensions.
A3: Business Use: Protects dimensional reporting from unmatched fact rows.
A4: Power BI Use: Retained as referential-integrity evidence; not loaded to the report model.
A5: Key Assumption: Zero missing dimension keys is required for PASS.
A7: Validation Rule | B7: Result | C7: Status
A8: Product keys must resolve to dim_product | B8: 0 | C8: =IF(B8=0,"PASS","FAIL") -> PASS
A9: Country keys must resolve to dim_country | B9: 0 | C9: =IF(B9=0,"PASS","FAIL") -> PASS
A10: Date keys must resolve to dim_date | B10: 0 | C10: =IF(B10=0,"PASS","FAIL") -> PASS

Sheet DQ05_Cancellation_Profile
A1: Cancellation Profile
A2: Purpose: Profile cancellations and manual adjustments before business analysis.
A3: Business Use: Separates commercial cancellations from stock corrections and write-offs.
A4: Power BI Use: Supports cancellation KPI definitions and data-quality notes.
A5: Key Assumption: Manual adjustments are distinct from cancellation invoices.
A7: Metric | B7: Value | C7: Unit | D7: Status
A8: Total Fact Rows | B8: 1067371 | C8: Rows | D8: PROFILED
A9: Cancellation Lines | B9: 19494 | C9: Rows | D9: REVIEWED
A10: Manual Adjustment Lines | B10: 3457 | C10: Rows | D10: REVIEWED
A11: Cancellation Value Removed | B11: 1526667.9 | C11: GBP | D11: REVIEWED
A12: Manual Adjustment Value | B12: 0 | C12: GBP | D12: REVIEWED
A14: Note: Manual adjustment value may be zero where source rows use zero unit price for stock corrections or write-offs.

Sheet Q01_Monthly_Revenue
A1: Monthly Revenue Performance
A2: Business Question: How is revenue trending month by month?
A3: SQL Technique: Aggregation, GROUP BY, CASE logic.
A4: Power BI Use: Revenue trend and KPI cards.
A5: Key Assumption: Gross excludes cancellations; net includes cancellation rows.
A7: Year | B7: Month Num | C7: Month Name | D7: Year Month | E7: Gross Revenue | F7: Net Revenue | G7: Orders | H7: Units | I7: Avg Order Value
A8: 2009 | B8: 12 | C8: December | D8: 2009-12 | E8: 825685.76 | F8: 799847.11 | G8: 1929 | H8: 430106 | I8: 428.04
A9: 2010 | B9: 1 | C9: January | D9: 2010-01 | E9: 652708.5 | F9: 624032.89 | G9: 1333 | H9: 379243 | I9: 489.65
A10: 2010 | B10: 2 | C10: February | D10: 2010-02 | E10: 553339.74 | F10: 533091.43 | G10: 1729 | H10: 375354 | I10: 320.03
A11: 2010 | B11: 3 | C11: March | D11: 2010-03 | E11: 833570.13 | F11: 765848.76 | G11: 1960 | H11: 493864 | I11: 425.29
A12: 2010 | B12: 4 | C12: April | D12: 2010-04 | E12: 627934.63 | F12: 590580.43 | G12: 1588 | H12: 358454 | I12: 395.42
A13: 2010 | B13: 5 | C13: May | D13: 2010-05 | E13: 659858.86 | F13: 615322.83 | G13: 2011 | H13: 380709 | I13: 328.12
A14: 2010 | B14: 6 | C14: June | D14: 2010-06 | E14: 752270.14 | F14: 679786.61 | G14: 1859 | H14: 403747 | I14: 404.66
A15: 2010 | B15: 7 | C15: July | D15: 2010-07 | E15: 606681.15 | F15: 575236.36 | G15: 1673 | H15: 308386 | I15: 362.63
A16: 2010 | B16: 8 | C16: August | D16: 2010-08 | E16: 697274.91 | F16: 656776.34 | G16: 1604 | H16: 458505 | I16: 434.71
A17: 2010 | B17: 9 | C17: September | D17: 2010-09 | E17: 924333.01 | F17: 853650.43 | G17: 2004 | H17: 573582 | I17: 461.24
A18: 2010 | B18: 10 | C18: October | D18: 2010-10 | E18: 1126558 | F18: 1045168.3 | G18: 2489 | H18: 613258 | I18: 452.61
A19: 2010 | B19: 11 | C19: November | D19: 2010-11 | E19: 1470272.5 | F19: 1422654.6 | G19: 3093 | H19: 691574 | I19: 475.35
... A32: 2011 | B32: 12 | C32: December | D32: 2011-12 | E32: 638810.68 | F32: 433686.01 | G32: 869 | H32: 309915 | I32: 735.11

Sheet Q02_Top_Customers
A1: Top Customers
A2: Business Question: Who are the highest-value customers?
A3: SQL Technique: Customer aggregation and ranking.
A4: Power BI Use: Top-customer and concentration analysis.
A5: Key Assumption: Contribution is stored as percentage points.
A7: Customer Id | B7: Customer Segment | C7: Revenue | D7: Orders | E7: Avg Order Value | F7: Revenue Share %
A8: 18102 | B8: High value | C8: 608821.65 | D8: 145 | E8: 4198.77 | F8: 0.0343
A9: 14646 | B9: High value | C9: 528602.52 | D9: 152 | E9: 3477.65 | F9: 0.0298
A10: 14156 | B10: High value | C10: 313946.37 | D10: 156 | E10: 2012.48 | F10: 0.0177
A11: 14911 | B11: High value | C11: 295972.63 | D11: 398 | E11: 743.65 | F11: 0.0167
A12: 17450 | B12: High value | C12: 246973.09 | D12: 51 | E12: 4842.61 | F12: 0.0139
A13: 13694 | B13: High value | C13: 196482.81 | D13: 143 | E13: 1374.01 | F13: 0.0111
A14: 17511 | B14: High value | C14: 175603.55 | D14: 60 | E14: 2926.73 | F14: 0.0099
A15: 16446 | B15: High value | C15: 168472.5 | D15: 2 | E15: 84236.25 | F15: 0.0095
A16: 16684 | B16: High value | C16: 147142.77 | D16: 55 | E16: 2675.32 | F16: 0.0083
A17: 12415 | B17: High value | C17: 144458.37 | D17: 28 | E17: 5159.23 | F17: 0.0081

Sheet Q03_Product_Category
A1: Product-Category Performance
A2: Business Question: Which categories drive revenue?
A3: SQL Technique: Category aggregation and share calculation.
A4: Power BI Use: Product mix visuals.
A5: Key Assumption: Categories are derived; uncategorised is retained.
A7: Category | B7: Revenue | C7: Units | D7: Product Count | E7: Revenue Share %
A8: Other or uncategorised | B8: 7931697.7 | C8: 4284103 | D8: 2651 | E8: 0.3944
A9: Bags and storage | B9: 3025978.4 | C9: 1612318 | D9: 370 | E9: 0.1505
A10: Home and living | B10: 2493799.6 | C10: 918325 | D10: 523 | E10: 0.124
A11: Kitchen and dining | B11: 2457941 | C11: 1374096 | D11: 370 | E11: 0.1222
A12: Lighting and candles | B12: 1787182.6 | C12: 976527 | D12: 476 | E12: 0.0889
A13: Stationery and gifts | B13: 1066462.3 | C13: 1012800 | D13: 282 | E13: 0.053
A14: Christmas and seasonal | B14: 817319.41 | C14: 548709 | D14: 181 | E14: 0.0406
A15: Jewellery and accessories | B15: 279518.15 | C15: 234676 | D15: 368 | E15: 0.0139
A16: Toys and games | B16: 251490.98 | C16: 113234 | D16: 58 | E16: 0.0125

Sheet Q04_Country_Performance
A1: Country Performance
A2: Business Question: Which countries perform strongest?
A3: SQL Technique: Dimensional joins and aggregation.
A4: Power BI Use: Geographic performance visuals.
A5: Key Assumption: GBP; no FX conversion; missing IDs excluded from customer counts.
A7: Country Name | B7: Region | C7: Active Customers | D7: Invoices | E7: Revenue | F7: Revenue Per Customer
A8: United Kingdom | B8: United Kingdom | C8: 5353 | D8: 33546 | E8: 14723148 | F8: 2750.45
A9: EIRE | B9: Eurozone | C9: 5 | D9: 567 | E9: 621631.11 | F9: 124326.22
A10: Netherlands | B10: Eurozone | C10: 22 | D10: 229 | E10: 554232.34 | F10: 25192.38
A11: Germany | B11: Eurozone | C11: 107 | D11: 789 | E11: 431262.46 | F11: 4030.49
A12: France | B12: Eurozone | C12: 95 | D12: 614 | E12: 355257.47 | F12: 3739.55
A13: Australia | B13: Rest of World | C13: 15 | D13: 95 | E13: 169968.11 | F13: 11331.21
A14: Spain | B14: Eurozone | C14: 41 | D14: 154 | E14: 109178.53 | F14: 2662.89
A15: Switzerland | B15: Other Europe | C15: 22 | D15: 90 | E15: 100365.34 | F15: 4562.06
A16: Sweden | B16: Other Europe | C16: 19 | D16: 104 | E16: 91549.72 | F16: 4818.41
A17: Denmark | B17: Other Europe | C17: 12 | D17: 43 | E17: 69862.19 | F17: 5821.85
A18: Belgium | B18: Eurozone | C18: 29 | D18: 149 | E18: 65753.42 | F18: 2267.36
A19: Norway | B19: Other Europe | C19: 13 | D19: 45 | E19: 60109.62 | F19: 4623.82
... A48: Nigeria | B48: Rest of World | C48: 1 | D48: 2 | E48: 140.39 | F48: 140.39
A50: Note: Small customer bases can inflate revenue-per-customer comparisons; interpret EIRE and other low-customer markets with care.

Sheet Q05_Cancellation_Analysis
A1: Cancellation Analysis
A2: Business Question: Where is cancellation exposure highest?
A3: SQL Technique: Conditional aggregation and rate logic.
A4: Power BI Use: Cancellation risk visuals.
A5: Key Assumption: Rate = cancelled value / gross non-cancelled sales.
A7: Country Name | B7: Region | C7: Cancelled Value | D7: Gross Sales Value | E7: Cancellation Rate
A8: United Kingdom | B8: United Kingdom | C8: 1329717.7 | D8: 17712302 | E8: 0.0751
A9: EIRE | B9: Eurozone | C9: 48912.23 | D9: 664431.78 | E9: 0.0736
A10: France | B10: Eurozone | C10: 28752.8 | D10: 356944.6 | E10: 0.0806
A11: Norway | B11: Other Europe | C11: 20866.59 | D11: 60109.62 | E11: 0.3471
A12: Spain | B12: Eurozone | C12: 17319.05 | D12: 109178.53 | E12: 0.1586
A13: Germany | B13: Eurozone | C13: 13273.9 | D13: 431262.46 | E13: 0.0308
A14: Singapore | B14: Rest of World | C14: 12158.9 | D14: 25317.06 | E14: 0.4803
A15: Hong Kong | B15: Rest of World | C15: 9855.02 | D15: 23894.32 | E15: 0.4124
A16: Netherlands | B16: Eurozone | C16: 5707.39 | D16: 554232.34 | E16: 0.0103
A17: Portugal | B17: Eurozone | C17: 4879.85 | D17: 58016.65 | E17: 0.0841
A18: Denmark | B18: Other Europe | C18: 4121.1 | D18: 69862.19 | E18: 0.059
A19: Sweden | B19: Other Europe | C19: 4094.3 | D19: 91903.72 | E19: 0.0445
... A50: Iceland | B50: Other Europe | C50: 0 | D50: 5633.32 | E50: 0
A52: Note: Very small markets may show cancellation rates above 100% where cancelled value exceeds gross sales value.

Sheet Q06_Running_Revenue
A1: Running Revenue Total
A2: Business Question: What is cumulative revenue momentum?
A3: SQL Technique: Cumulative SUM window function.
A4: Power BI Use: Cumulative trend line.
A5: Key Assumption: Months follow chronological order.
A7: Year | B7: Month Num | C7: Month Name | D7: Year Month | E7: Monthly Revenue | F7: Running Total Revenue
A8: 2009 | B8: 12 | C8: December | D8: 2009-12 | E8: 825685.76 | F8: 825685.76
A9: 2010 | B9: 1 | C9: January | D9: 2010-01 | E9: 652708.5 | F9: 1478394.3
A10: 2010 | B10: 2 | C10: February | D10: 2010-02 | E10: 553339.74 | F10: 2031734
A11: 2010 | B11: 3 | C11: March | D11: 2010-03 | E11: 833570.13 | F11: 2865304.1
A12: 2010 | B12: 4 | C12: April | D12: 2010-04 | E12: 627934.63 | F12: 3493238.8
A13: 2010 | B13: 5 | C13: May | D13: 2010-05 | E13: 659858.86 | F13: 4153097.6
A14: 2010 | B14: 6 | C14: June | D14: 2010-06 | E14: 752270.14 | F14: 4905367.8
A15: 2010 | B15: 7 | C15: July | D15: 2010-07 | E15: 606681.15 | F15: 5512048.9
A16: 2010 | B16: 8 | C16: August | D16: 2010-08 | E16: 697274.91 | F16: 6209323.8
A17: 2010 | B17: 9 | C17: September | D17: 2010-09 | E17: 924333.01 | F17: 7133656.8
A18: 2010 | B18: 10 | C18: October | D18: 2010-10 | E18: 1126558 | F18: 8260214.9
A19: 2010 | B19: 11 | C19: November | D19: 2010-11 | E19: 1470272.5 | F19: 9730487.3
... A32: 2011 | B32: 12 | C32: December | D32: 2011-12 | E32: 638810.68 | F32: 20813918

Sheet Q07_Customer_Cohorts
A1: Customer Acquisition Cohorts
A2: Business Question: How valuable is each acquisition cohort?
A3: SQL Technique: First-purchase cohort logic.
A4: Power BI Use: Cohort analysis.
A5: Key Assumption: Requires identifiable customers.
A7: Cohort Month | B7: Cohort Customers | C7: Total Revenue To Date | D7: Revenue Per Customer
A8: 2009-12 | B8: 1045 | C8: 9058705.3 | D8: 8668.62
A9: 2010-01 | B9: 394 | C9: 1225886.1 | D9: 3111.39
A10: 2010-02 | B10: 363 | C10: 948918.82 | D10: 2614.1
A11: 2010-03 | B11: 436 | C11: 1185768.7 | D11: 2719.65
A12: 2010-04 | B12: 291 | C12: 536518.07 | D12: 1843.7
A13: 2010-05 | B13: 254 | C13: 388721.76 | D13: 1530.4
A14: 2010-06 | B14: 269 | C14: 590893.23 | D14: 2196.63
A15: 2010-07 | B15: 183 | C15: 311451.5 | D15: 1701.92
A16: 2010-08 | B16: 158 | C16: 269310.88 | D16: 1704.5
A17: 2010-09 | B17: 242 | C17: 577997.46 | D17: 2388.42
A18: 2010-10 | B18: 379 | C18: 684405.02 | D18: 1805.82
A19: 2010-11 | B19: 322 | C19: 364791.44 | D19: 1132.89
... A32: 2011-12 | B32: 28 | C32: 23844.09 | D32: 851.57

Sheet Q08_Regional_Ranking
A1: Regional Revenue Ranking
A2: Business Question: How do regions rank quarterly?
A3: SQL Technique: RANK window partitioned by period.
A4: Power BI Use: Regional ranking visuals.
A5: Key Assumption: Ranks recalculate within year-quarter.
A7: Year | B7: Quarter | C7: Region | D7: Revenue | E7: Region Rank
A8: 2009 | B8: 4 | C8: United Kingdom | D8: 750317.22 | E8: 1
A9: 2009 | B9: 4 | C9: Eurozone | D9: 70280.07 | E9: 2
A10: 2009 | B10: 4 | C10: Other Europe | D10: 4158.67 | E10: 3
A11: 2009 | B11: 4 | C11: Rest of World | D11: 929.8 | E11: 4
A12: 2010 | B12: 1 | C12: United Kingdom | D12: 1688090.6 | E12: 1
A13: 2010 | B13: 1 | C13: Eurozone | D13: 274794.05 | E13: 2
A14: 2010 | B14: 1 | C14: Other Europe | D14: 64418.36 | E14: 3
A15: 2010 | B15: 1 | C15: Rest of World | D15: 11280.27 | E15: 4
A16: 2010 | B16: 1 | C16: Unknown | D16: 1035.1 | E16: 5
A17: 2010 | B17: 2 | C17: United Kingdom | D17: 1743615.7 | E17: 1
A18: 2010 | B18: 2 | C18: Eurozone | D18: 230047.02 | E18: 2
A19: 2010 | B19: 2 | C19: Other Europe | D19: 47446.58 | E19: 3
... A50: 2011 | B50: 4 | C50: Unknown | D50: 965.75 | E50: 5

Sheet Q09_MoM_Growth
A1: Month-on-Month Growth
A2: Business Question: What is monthly revenue growth?
A3: SQL Technique: LAG, absolute and percentage change.
A4: Power BI Use: Growth and variance visuals.
A5: Key Assumption: First month has no prior; percentages are points.
A7: Year | B7: Month Num | C7: Month Name | D7: Year Month | E7: Revenue | F7: Prior Month Revenue | G7: Absolute Change | H7: Pct Change
A8: 2009 | B8: 12 | C8: December | D8: 2009-12 | E8: 825685.76
A9: 2010 | B9: 1 | C9: January | D9: 2010-01 | E9: 652708.5 | F9: 825685.76 | G9: -172977.26 | H9: -0.2095
A10: 2010 | B10: 2 | C10: February | D10: 2010-02 | E10: 553339.74 | F10: 652708.5 | G10: -99368.77 | H10: -0.1522
A11: 2010 | B11: 3 | C11: March | D11: 2010-03 | E11: 833570.13 | F11: 553339.74 | G11: 280230.4 | H11: 0.5064
A12: 2010 | B12: 4 | C12: April | D12: 2010-04 | E12: 627934.63 | F12: 833570.13 | G12: -205635.5 | H12: -0.2467
A13: 2010 | B13: 5 | C13: May | D13: 2010-05 | E13: 659858.86 | F13: 627934.63 | G13: 31924.23 | H13: 0.0508
A14: 2010 | B14: 6 | C14: June | D14: 2010-06 | E14: 752270.14 | F14: 659858.86 | G14: 92411.28 | H14: 0.14
A15: 2010 | B15: 7 | C15: July | D15: 2010-07 | E15: 606681.15 | F15: 752270.14 | G15: -145588.99 | H15: -0.1935
A16: 2010 | B16: 8 | C16: August | D16: 2010-08 | E16: 697274.91 | F16: 606681.15 | G16: 90593.76 | H16: 0.1493
A17: 2010 | B17: 9 | C17: September | D17: 2010-09 | E17: 924333.01 | F17: 697274.91 | G17: 227058.1 | H17: 0.3256
A18: 2010 | B18: 10 | C18: October | D18: 2010-10 | E18: 1126558 | F18: 924333.01 | G18: 202225.03 | H18: 0.2188
A19: 2010 | B19: 11 | C19: November | D19: 2010-11 | E19: 1470272.5 | F19: 1126558 | G19: 343714.44 | H19: 0.3051
A20: 2010 | B20: 12 | C20: December | D20: 2010-12 | E20: 1262598.8 | F20: 1470272.5 | G20: -207673.69 | H20: -0.1412
... A32: 2011 | B32: 12 | C32: December | D32: 2011-12 | E32: 638810.68 | F32: 1509496.3 | G32: -870685.65 | H32: -0.5768
A34: Note: The first month has no prior comparison; Prior Month Revenue, Absolute Change, and Pct Change are intentionally blank.

Sheet Q10_Rolling_Revenue
A1: Rolling Revenue Trend
A2: Business Question: What is the smoothed revenue trend?
A3: SQL Technique: Three-month windowed AVG.
A4: Power BI Use: Revenue and rolling-average trend.
A5: Key Assumption: Opening periods use available months.
A7: Year | B7: Month Num | C7: Month Name | D7: Year Month | E7: Revenue | F7: Rolling 3 Month Avg
A8: 2009 | B8: 12 | C8: December | D8: 2009-12 | E8: 825685.76 | F8: 825685.76
A9: 2010 | B9: 1 | C9: January | D9: 2010-01 | E9: 652708.5 | F9: 739197.13
A10: 2010 | B10: 2 | C10: February | D10: 2010-02 | E10: 553339.74 | F10: 677244.67
A11: 2010 | B11: 3 | C11: March | D11: 2010-03 | E11: 833570.13 | F11: 679872.79
A12: 2010 | B12: 4 | C12: April | D12: 2010-04 | E12: 627934.63 | F12: 671614.83
A13: 2010 | B13: 5 | C13: May | D13: 2010-05 | E13: 659858.86 | F13: 707121.21
A14: 2010 | B14: 6 | C14: June | D14: 2010-06 | E14: 752270.14 | F14: 680021.21
A15: 2010 | B15: 7 | C15: July | D15: 2010-07 | E15: 606681.15 | F15: 672936.72
A16: 2010 | B16: 8 | C16: August | D16: 2010-08 | E16: 697274.91 | F16: 685408.73
A17: 2010 | B17: 9 | C17: September | D17: 2010-09 | E17: 924333.01 | F17: 742763.02
A18: 2010 | B18: 10 | C18: October | D18: 2010-10 | E18: 1126558 | F18: 916055.32
A19: 2010 | B19: 11 | C19: November | D19: 2010-11 | E19: 1470272.5 | F19: 1173721.2
... A32: 2011 | B32: 12 | C32: December | D32: 2011-12 | E32: 638810.68 | F32: 1101095.4
